<Page class="page"
      navigatingTo="onNavigatingTo"
      actionBarHidden="true"
      xmlns="http://schemas.nativescript.org/tns.xsd"
      xmlns:x="nativescript-statusbar"
      backgroundSpanUnderStatusBar="true">

    <ActionBar >
        <ActionItem icon="res://menu"
                    ios:visibility="collapsed"
                    tap="onDrawerButtonTap"
                    android.position="right">
        </ActionItem>
        <ActionItem icon="res://navigation/menu"
                    android:visibility="collapsed"
                    tap="onDrawerButtonTap"
                    ios.position="right">
        </ActionItem>
    </ActionBar>
    <ios>
        <x:StatusBar ios:barStyle="light" barColor="rgba(0, 0, 0,0.0)"/>
    </ios>
    <android>
        <x:StatusBar ios:barStyle="light" barColor="rgb(34, 56, 79)"/>
    </android>



    <GridLayout horizontalAlignment="stretch" verticalAlignment="stretch" height="100%">
        <!--        Top-->
        <GridLayout verticalAlignment="top">
            <StackLayout orientation="vertical">
                <!--    Background squares    -->
                <StackLayout  class="two-color-gradient" width="100%" height="20%" verticalAlignment="center"/>
                <StackLayout id="bottom_bar" height="5" width="100%" backgroundColor="#107dd0"/>

                <GridLayout columns="*,*,*,*,*" class="main_image" id="main_image" backgroundImage="~/images/image1.jpg" marginBottom="30" height="34%">
                    <GridLayout  col="0" id="bg_0" height="35%" width="35%" verticalAlignment="bottom">
                        <StackLayout id="icon_0" backgroundImage="~/images/icon_home/CDN.png" backgroundColor="white" class="circle" verticalAlignment="center"/>
                    </GridLayout>
                    <GridLayout  col="1" id="bg_1" height="35%" width="35%" verticalAlignment="bottom">
                        <StackLayout id="icon_1" backgroundColor="white" class="circle" verticalAlignment="center"/>
                    </GridLayout>
                    <GridLayout   col="2" id="bg_2" height="35%" width="35%" verticalAlignment="bottom">
                        <StackLayout id="icon_2" backgroundColor="white" class="circle" verticalAlignment="center"/>
                    </GridLayout>
                    <GridLayout  col="3" id="bg_3" height="35%" width="35%" verticalAlignment="bottom">
                        <StackLayout id="icon_3" backgroundColor="white" class="circle" verticalAlignment="center"/>
                    </GridLayout>
                    <GridLayout col="4" id="bg_4" height="35%" width="35%" verticalAlignment="bottom">
                        <StackLayout id="icon_4" backgroundColor="white" class="circle" verticalAlignment="center"/>
                    </GridLayout>
                </GridLayout>
                <!--    Buttons    -->
                <GridLayout rows="*,*,*" height="25%" marginRight="10" marginLeft="10" verticalAlignment="top" >
                    <StackLayout orientation="horizontal" row="0" horizontalAlignment="stretch" verticalAlignment="top">
                        <Button  class="btn" text="Avvisi" horizontalAlignment="center" width="50%" marginRight="5" ontap="onTapAvvisi" />
                        <Button  class="btn" text="Notizie" horizontalAlignment="center" width="50%" tap="onTapNotizie"/>
                    </StackLayout>
                    <StackLayout orientation="horizontal" row="1" horizontalAlignment="stretch" verticalAlignment="top">
                        <Button  class="btn" text="Studia Con Noi" backgroundColor="#22384f" color="white" horizontalAlignment="center" width="50%" marginRight="5" tap="onTapStudia"/>
                        <Button  class="btn" text="Eventi" horizontalAlignment="center" width="50%" ontap="onTapEventi" />
                    </StackLayout>
                    <GridLayout row="2" columns="auto,auto,auto" verticalAlignment="top" horizontalAlignment="center">
                        <StackLayout col="0" horizontalAlignment="right" marginRight="5">
                            <Button class="circle" backgroundColor="#22384f" tap="onTapFood" backgroundImage="~/images/icon/food.png" height="30" width="30"/>
                        </StackLayout>
                        <StackLayout col="1" horizontalAlignment="left" marginLeft="5" marginRight="5">
                            <Button class="circle" backgroundColor="#22384f" tap="onTapMeteo" backgroundImage="~/images/icon/storm.png" height="30" width="30"/>
                        </StackLayout>
                        <StackLayout col="2" horizontalAlignment="left" marginLeft="5">
                            <Button class="circle" backgroundColor="#22384f" tap="onTapTrasporti" backgroundImage="~/images/icon/front-bus.png" height="30" width="30"/>
                        </StackLayout>
                    </GridLayout>
                </GridLayout>

            </StackLayout>
            <!--    Testo sovrapposto    -->

            <GridLayout verticalAlignment="top">
                <ios>
                    <Label class="topTitle" horizontalAlignment="left" text="Università degli Studi di Napoli&#xA;Parthenope" textWrap="true" marginRight="5" marginLeft="5" marginTop="30"/>
                </ios>
                <android>
                    <Label class="topTitle" horizontalAlignment="right" text="Università degli Studi di Napoli&#xA;Parthenope" textWrap="true" marginRight="10" marginTop="5" textAlignment="right"/>
                </android>

            </GridLayout>
            <Image  src="~/images/logo_new.png" horizontalAlignment="right" verticalAlignment="top" height="170" width="170" marginTop="90" marginRight="10"/>



        </GridLayout>
<!--Bottom/Social-->
        <GridLayout verticalAlignment="bottom">
            <StackLayout width="100%" height="12%" backgroundColor="#107dd0"/>
        </GridLayout>
        <StackLayout orientation="horizontal" verticalAlignment="bottom" marginBottom="50" horizontalAlignment="center">
            <Button class="roundedBtn" text="" marginRight="10" backgroundImage="~/images/social/fb.png" ontap="ontap_fb"/>
            <Button  class="roundedBtn" text="" marginRight="10" backgroundImage="~/images/social/twi.png" ontap="ontap_twi"/>
            <Button  class="roundedBtn" text="" marginRight="10" backgroundImage="~/images/social/insta.png" ontap="ontap_insta"/>
            <Button  class="roundedBtn" text="" marginRight="10" backgroundImage="~/images/social/you.png" ontap="ontap_you"/>
            <Button  class="roundedBtn" text="" backgroundImage="~/images/social/linkedin.png" ontap="ontap_linkedin"/>

        </StackLayout>
        <StackLayout orientation="vertical" verticalAlignment="bottom">
            <Label text="Universitá degli Studi di Napoli ''Parthenope''" horizontalAlignment="center" color="white"  marginBottom="5" fontSize="10"/>
            <Label id="version" horizontalAlignment="center" color="white" verticalAlignment="bottom" marginBottom="5" fontSize="10"/>
        </StackLayout>

        <ios>
            <Button class="myMenu" backgroundImage="res://navigation/menu" backgroundColor="#000000ff" verticalAlignment="top" ontap="onDrawerButtonTap" horizontalAlignment="right" height="20" width="20" marginRight="15" marginTop="15"/>
        </ios>
        <android>
            <Button class="myMenu" backgroundImage="res://menu" ontap="onDrawerButtonTap" verticalAlignment="top" horizontalAlignment="left" height="25" width="25" margin="20 5 10 5"/>
        </android>

        <StackLayout id="activityIndicator" visibility="collapsed" verticalAlignment="center" height="100%" width="100%" backgroundColor="rgba(0,0,0,0.5)">
            <Label text="Connessione..." horizontalAlignment="center" class="textPrimary"/>
            <ActivityIndicator horizontalAlignment="center" color="white" busy="true"/>
        </StackLayout>
    </GridLayout>
</Page>
